ipfinder/__init__.py
ipfinder/externip.py
iply-0.0.1.dist-info/METADATA
iply-0.0.1.dist-info/WHEEL
iply-0.0.1.dist-info/entry_points.txt
iply-0.0.1.dist-info/top_level.txt
iply-0.0.1.dist-info/RECORD
